RPA_Cloud_Google.libspec
RPA/Cloud/Google/__init__.py
RPA/Cloud/Google/keywords/__init__.py
RPA/Cloud/Google/keywords/apps_script.py
RPA/Cloud/Google/keywords/base.py
RPA/Cloud/Google/keywords/context.py
RPA/Cloud/Google/keywords/document_ai.py
RPA/Cloud/Google/keywords/drive.py
RPA/Cloud/Google/keywords/enums.py
RPA/Cloud/Google/keywords/gmail.py
RPA/Cloud/Google/keywords/natural_language.py
RPA/Cloud/Google/keywords/sheets.py
RPA/Cloud/Google/keywords/speech_to_text.py
RPA/Cloud/Google/keywords/storage.py
RPA/Cloud/Google/keywords/text_to_speech.py
RPA/Cloud/Google/keywords/translation.py
RPA/Cloud/Google/keywords/video_intelligence.py
RPA/Cloud/Google/keywords/vision.py
RPA/scripts/google_authenticate.py
rpaframework_google-9.0.2.dist-info/entry_points.txt
rpaframework_google-9.0.2.dist-info/LICENSE
rpaframework_google-9.0.2.dist-info/METADATA
rpaframework_google-9.0.2.dist-info/WHEEL
rpaframework_google-9.0.2.dist-info/RECORD
