Metadata-Version: 2.1
Name: rpaframework-google
Version: 9.0.2
Summary: Google library for RPA Framework
Home-page: https://rpaframework.org/
License: Apache-2.0
Keywords: robotframework,rpa,automation,google
Author: RPA Framework
Author-email: rpafw@robocorp.com
Requires-Python: >=3.8,<4.0
Classifier: Development Status :: 5 - Production/Stable
Classifier: Framework :: Robot Framework
Classifier: Framework :: Robot Framework :: Library
Classifier: Intended Audience :: Developers
Classifier: License :: OSI Approved :: Apache Software License
Classifier: Operating System :: OS Independent
Classifier: Programming Language :: Python :: 3
Classifier: Programming Language :: Python :: 3.8
Classifier: Programming Language :: Python :: 3.9
Classifier: Programming Language :: Python :: 3.10
Classifier: Programming Language :: Python :: 3.11
Classifier: Programming Language :: Python :: 3.12
Classifier: Topic :: Software Development :: Libraries
Classifier: Topic :: Software Development :: Libraries :: Python Modules
Requires-Dist: google-api-python-client (>=2.58.0,<3.0.0)
Requires-Dist: google-auth-httplib2 (>=0.1.0,<0.2.0)
Requires-Dist: google-auth-oauthlib (>=0.5.2,<0.6.0)
Requires-Dist: google-cloud-documentai (>=2.0.1,<3.0.0)
Requires-Dist: google-cloud-language (>=2.5.2,<3.0.0)
Requires-Dist: google-cloud-speech (>=2.15.1,<3.0.0)
Requires-Dist: google-cloud-storage (>=2.5.0,<3.0.0)
Requires-Dist: google-cloud-texttospeech (>=2.12.1,<3.0.0)
Requires-Dist: google-cloud-translate (>=3.8.1,<4.0.0)
Requires-Dist: google-cloud-videointelligence (>=2.8.1,<3.0.0)
Requires-Dist: google-cloud-vision (>=3.1.1,<4.0.0)
Requires-Dist: grpcio (>=1.48.1,<2.0.0)
Requires-Dist: robotframework (>=4.0.0,!=4.0.1,!=6.1.0,<7.0.0)
Requires-Dist: rpaframework-core (>=11.3.1,<12.0.0)
Project-URL: Documentation, https://rpaframework.org/
Project-URL: Repository, https://github.com/robocorp/rpaframework
